keras-svm/__init__.py
keras-svm/sequential_with_svm.py
keras_svm/__init__.py
keras_svm/model_svm_wrapper.py
keras_svm/sequential_with_svm.py
keras_svm-1.0.0b10.dist-info/LICENSE.txt
keras_svm-1.0.0b10.dist-info/METADATA
keras_svm-1.0.0b10.dist-info/RECORD
keras_svm-1.0.0b10.dist-info/WHEEL
keras_svm-1.0.0b10.dist-info/top_level.txt
